[{
    "title":"1",
    "description": "When raw*, the image will be rendered as a single image wrappers, sizers or other responsive behavior.",
    "icon": "url//jbfjfvv"
},
{
    "title":"2",
    "description": "When raw*, the image will be rendered as a single image wrappers, sizers or other responsive behavior.",
    "icon": "url//jbfjfvv"
},
{
    "title":"1",
    "description": "When raw*, the image will be rendered as a single image wrappers, sizers or other responsive behavior.",
    "icon": "url//jbfjfvv"
},
{
    "title":"2",
    "description": "When raw*, the image will be rendered as a single image wrappers, sizers or other responsive behavior.",
    "icon": "url//jbfjfvv"
},
{
    "title":"1",
    "description": "When raw*, the image will be rendered as a single image wrappers, sizers or other responsive behavior.",
    "icon": "url//jbfjfvv"
},
{
    "title":"2",
    "description": "When raw*, the image will be rendered as a single image wrappers, sizers or other responsive behavior.",
    "icon": "url//jbfjfvv"
},
{
    "title":"1",
    "description": "When raw*, the image will be rendered as a single image wrappers, sizers or other responsive behavior.",
    "icon": "url//jbfjfvv"
},
{
    "title":"2",
    "description": "When raw*, the image will be rendered as a single image wrappers, sizers or other responsive behavior.",
    "icon": "url//jbfjfvv"
}
,
{
    "title":"1",
    "description": "When raw*, the image will be rendered as a single image wrappers, sizers or other responsive behavior.",
    "icon": "url//jbfjfvv"
},
{
    "title":"2",
    "description": "When raw*, the image will be rendered as a single image wrappers, sizers or other responsive behavior.",
    "icon": "url//jbfjfvv"
}
,
{
    "title":"1",
    "description": "When raw*, the image will be rendered as a single image wrappers, sizers or other responsive behavior.",
    "icon": "url//jbfjfvv"
},
{
    "title":"2",
    "description": "When raw*, the image will be rendered as a single image wrappers, sizers or other responsive behavior.",
    "icon": "url//jbfjfvv"
}
]